placaEcuador/__init__.py
placaEcuador-1.dist-info/LICENSE
placaEcuador-1.dist-info/METADATA
placaEcuador-1.dist-info/WHEEL
placaEcuador-1.dist-info/top_level.txt
placaEcuador-1.dist-info/RECORD
