Metadata-Version: 2.1
Name: placaEcuador
Version: 1
Summary: A package with a tool to check if you can be on the  road of Quito - Ecuador
Home-page: https://github.com/alexandro591/Pico-Placa
Author: Alexandro Tapia
Author-email: alexandrotapiaflores@gmail.com
License: UNKNOWN
Platform: UNKNOWN
Classifier: Programming Language :: Python :: 3
Classifier: License :: OSI Approved :: MIT License
Classifier: Operating System :: OS Independent
Requires-Python: >=3.6
